dxi_nlp-0.1.7-py3.9-nspkg.pth
dxi_nlp/labelling/__init__.py
dxi_nlp/labelling/dxi_labelbox.py
dxi_nlp/relevancy/__init__.py
dxi_nlp/relevancy/relevancy_utils.py
dxi_nlp/relevancy/sentence.py
dxi_nlp-0.1.7.dist-info/LICENSE
dxi_nlp-0.1.7.dist-info/METADATA
dxi_nlp-0.1.7.dist-info/WHEEL
dxi_nlp-0.1.7.dist-info/namespace_packages.txt
dxi_nlp-0.1.7.dist-info/top_level.txt
dxi_nlp-0.1.7.dist-info/RECORD
