Metadata-Version: 2.1
Name: dxi-nlp
Version: 0.1.7
Summary: UNKNOWN
Home-page: https://github.com/Edelman-DxI/dxi-nlp.git
Author: Amit Prusty
Author-email: amit.prusty@edelmandxi.com
License: Private
Platform: UNKNOWN
License-File: LICENSE
Requires-Dist: numpy
Requires-Dist: pandas
Requires-Dist: spacy
Requires-Dist: boto3
Requires-Dist: s3fs
Requires-Dist: matplotlib
Requires-Dist: tqdm
Requires-Dist: pyarrow
Requires-Dist: labelbox
